cloudparing/aws_cdk/__init__.py
cloudparing/aws_cdk/py.typed
cloudparing/aws_cdk/_jsii/__init__.py
cloudparing/aws_cdk/_jsii/aws-cdk-lib@0.0.19.jsii.tgz
cloudparing.aws_cdk-0.0.19.dist-info/LICENSE
cloudparing.aws_cdk-0.0.19.dist-info/METADATA
cloudparing.aws_cdk-0.0.19.dist-info/WHEEL
cloudparing.aws_cdk-0.0.19.dist-info/top_level.txt
cloudparing.aws_cdk-0.0.19.dist-info/RECORD
